pymagicc/__init__.py
pymagicc/_version.py
pymagicc/config.py
pymagicc/core.py
pymagicc/default_config.nml
pymagicc/errors.py
pymagicc/magicc_time.py
pymagicc/utils.py
pymagicc/MAGICC6/Installation_and_Use_Instructions.txt
pymagicc/MAGICC6/License_MAGICC6Executable.txt
pymagicc/MAGICC6/out/.gitkeep
pymagicc/MAGICC6/run/1PCTCO2_CO2_CONC.IN
pymagicc/MAGICC6/run/ABRUPT2XCO2_CO2_CONC.IN
pymagicc/MAGICC6/run/EDGAR_NOXB_EMIS.IN
pymagicc/MAGICC6/run/EDGAR_NOXI_EMIS.IN
pymagicc/MAGICC6/run/GISS_BCB_OT.IN
pymagicc/MAGICC6/run/GISS_BCB_RF.IN
pymagicc/MAGICC6/run/GISS_BCI_OT.IN
pymagicc/MAGICC6/run/GISS_BCI_RF.IN
pymagicc/MAGICC6/run/GISS_BCSNOW_RF.IN
pymagicc/MAGICC6/run/GISS_LANDUSE_RF.IN
pymagicc/MAGICC6/run/GISS_NOX_RF.IN
pymagicc/MAGICC6/run/GISS_OCB_OT.IN
pymagicc/MAGICC6/run/GISS_OCB_RF.IN
pymagicc/MAGICC6/run/GISS_OCI_OT.IN
pymagicc/MAGICC6/run/GISS_OCI_RF.IN
pymagicc/MAGICC6/run/GISS_OCN_OT.IN
pymagicc/MAGICC6/run/GISS_SOXI_OT.IN
pymagicc/MAGICC6/run/GISS_SOXNB_OT.IN
pymagicc/MAGICC6/run/GISS_SOX_RF.IN
pymagicc/MAGICC6/run/GISS_SS_OT.IN
pymagicc/MAGICC6/run/HISTRCP2009_SOLAR_RF.IN
pymagicc/MAGICC6/run/HISTRCP45SCP45to3PD_SOLAR_RF.IN
pymagicc/MAGICC6/run/HISTRCP45_SOLAR_RF.IN
pymagicc/MAGICC6/run/HISTRCP60_2300_SOLAR_RF.IN
pymagicc/MAGICC6/run/HISTRCP6SCP6to45_SOLAR_RF.IN
pymagicc/MAGICC6/run/HISTRCP6_SOLAR_RF.IN
pymagicc/MAGICC6/run/HISTRCP85_SOLAR_RF.IN
pymagicc/MAGICC6/run/HISTRCP_BCB_EMIS.IN
pymagicc/MAGICC6/run/HISTRCP_BCI_EMIS.IN
pymagicc/MAGICC6/run/HISTRCP_C2F6_CONC.IN
pymagicc/MAGICC6/run/HISTRCP_C2F6_EMIS.IN
pymagicc/MAGICC6/run/HISTRCP_C6F14I_EMIS.IN
pymagicc/MAGICC6/run/HISTRCP_C6F14_CONC.IN
pymagicc/MAGICC6/run/HISTRCP_C6F14_EMIS.IN
pymagicc/MAGICC6/run/HISTRCP_CF4_CONC.IN
pymagicc/MAGICC6/run/HISTRCP_CF4_EMIS.IN
pymagicc/MAGICC6/run/HISTRCP_CH4B_EMIS.IN
pymagicc/MAGICC6/run/HISTRCP_CH4I_EMIS.IN
pymagicc/MAGICC6/run/HISTRCP_CH4_CONC.IN
pymagicc/MAGICC6/run/HISTRCP_CO2B_EMIS.IN
pymagicc/MAGICC6/run/HISTRCP_CO2I_EMIS.IN
pymagicc-2.1.5.dist-info/LICENSE
pymagicc-2.1.5.dist-info/METADATA
pymagicc-2.1.5.dist-info/WHEEL
pymagicc-2.1.5.dist-info/top_level.txt
pymagicc-2.1.5.dist-info/RECORD
