Metadata-Version: 2.1
Name: pymagicc
Version: 2.1.5
Summary: Python wrapper for the simple climate model MAGICC
Home-page: https://github.com/openscm/pymagicc
Author: Robert Gieseke, Zeb Nicholls, Jared Lewis, Sven Willner, Matthias Mengel
Author-email: rob.g@web.de, zebedee.nicholls@climate-energy-college.org, jared.lewis@climate-energy-college.org, sven.willner@pik-potsdam.de, matthias.mengel@pik-potsdam.de
License: 3-Clause BSD License
Project-URL: Bug Reports, https://github.com/openscm/pymagicc/issues
Project-URL: Documentation, https://pymagicc.readthedocs.io/en/latest
Project-URL: Source, https://github.com/openscm/pymagicc
Keywords: simple climate model MAGICC python
Classifier: Development Status :: 4 - Beta
Classifier: Intended Audience :: Developers
Classifier: License :: OSI Approved :: BSD License
Classifier: Operating System :: OS Independent
Classifier: Programming Language :: Python :: 3.9
Classifier: Programming Language :: Python :: 3.10
Classifier: Programming Language :: Python :: 3.11
License-File: LICENSE
Requires-Dist: pandas-datapackage-reader
Requires-Dist: f90nml
Requires-Dist: PyYAML
Requires-Dist: scmdata
Requires-Dist: pandas
Requires-Dist: versioneer
Provides-Extra: deploy
Requires-Dist: setuptools >=38.6.0 ; extra == 'deploy'
Requires-Dist: twine >=1.11.0 ; extra == 'deploy'
Requires-Dist: wheel >=0.31.0 ; extra == 'deploy'
Provides-Extra: dev
Requires-Dist: bandit ; extra == 'dev'
Requires-Dist: black ; extra == 'dev'
Requires-Dist: flake8 ; extra == 'dev'
Requires-Dist: isort >=5 ; extra == 'dev'
Requires-Dist: nbdime ; extra == 'dev'
Requires-Dist: pydocstyle ; extra == 'dev'
Requires-Dist: pylint ; extra == 'dev'
Requires-Dist: notebook ; extra == 'dev'
Requires-Dist: expectexception ; extra == 'dev'
Requires-Dist: seaborn ; extra == 'dev'
Requires-Dist: pyam-iamc >=0.3.0 ; extra == 'dev'
Requires-Dist: nbval ; extra == 'dev'
Requires-Dist: pytest >=7 ; extra == 'dev'
Requires-Dist: pytest-benchmark ; extra == 'dev'
Requires-Dist: pytest-cov ; extra == 'dev'
Requires-Dist: pytest-mock ; extra == 'dev'
Requires-Dist: pytest-xdist ; extra == 'dev'
Requires-Dist: codecov ; extra == 'dev'
Requires-Dist: goodtables ; extra == 'dev'
Requires-Dist: scipy ; extra == 'dev'
Requires-Dist: sphinx >2.1 ; extra == 'dev'
Requires-Dist: sphinx-rtd-theme ; extra == 'dev'
Requires-Dist: sphinx-autodoc-typehints ; extra == 'dev'
Requires-Dist: pydoc-markdown ; extra == 'dev'
Requires-Dist: setuptools >=38.6.0 ; extra == 'dev'
Requires-Dist: twine >=1.11.0 ; extra == 'dev'
Requires-Dist: wheel >=0.31.0 ; extra == 'dev'
Provides-Extra: docs
Requires-Dist: sphinx >2.1 ; extra == 'docs'
Requires-Dist: sphinx-rtd-theme ; extra == 'docs'
Requires-Dist: sphinx-autodoc-typehints ; extra == 'docs'
Requires-Dist: pydoc-markdown ; extra == 'docs'
Provides-Extra: notebooks
Requires-Dist: notebook ; extra == 'notebooks'
Requires-Dist: expectexception ; extra == 'notebooks'
Requires-Dist: seaborn ; extra == 'notebooks'
Requires-Dist: pyam-iamc >=0.3.0 ; extra == 'notebooks'
Provides-Extra: tests
Requires-Dist: nbval ; extra == 'tests'
Requires-Dist: pytest >=7 ; extra == 'tests'
Requires-Dist: pytest-benchmark ; extra == 'tests'
Requires-Dist: pytest-cov ; extra == 'tests'
Requires-Dist: pytest-mock ; extra == 'tests'
Requires-Dist: pytest-xdist ; extra == 'tests'
Requires-Dist: codecov ; extra == 'tests'
Requires-Dist: goodtables ; extra == 'tests'
Requires-Dist: scipy ; extra == 'tests'
Requires-Dist: seaborn ; extra == 'tests'
